zassist/__init__.py
zassist/commonlib/__init__.py
zassist/commonlib/keyboard.py
zassist/commonlib/mouse.py
zassist/commonlib/network.py
zassist/commonlib/password.py
zassist/commonlib/public_const.py
zassist/commonlib/regedit.py
zassist/commonlib/screen.py
zassist/commonlib/system.py
zassist/commonlib/window.py
zassist/dll/HookDll.dll
zassist/dll/assistlib.dll
zassist/utils/__init__.py
zassist/utils/util.py
zassist-0.9.1.dist-info/METADATA
zassist-0.9.1.dist-info/RECORD
zassist-0.9.1.dist-info/WHEEL
zassist-0.9.1.dist-info/top_level.txt
