Metadata-Version: 2.1
Name: zassist
Version: 0.9.1
Summary: 制作游戏辅助常用模块
Home-page: https://pypi.org/
Author: zlyuan
Author-email: 1277260932@qq.com
License: GNU GENERAL PUBLIC LICENSE
Platform: all
Classifier: Environment :: Web Environment
Classifier: Intended Audience :: Developers
Classifier: Operating System :: OS Independent
Classifier: Programming Language :: Python :: 3
Requires-Dist: pywin32
Requires-Dist: psutil
Requires-Dist: pythonnet
Requires-Dist: requests
